h5sparse/__init__.py
h5sparse/h5sparse.py
h5sparse/tests.py
h5sparse-0.1.0.dist-info/LICENSE
h5sparse-0.1.0.dist-info/METADATA
h5sparse-0.1.0.dist-info/WHEEL
h5sparse-0.1.0.dist-info/top_level.txt
h5sparse-0.1.0.dist-info/RECORD
